{"version":3,"kind":"Notebook","sha256":"f1acf5d600cf5a4310f97186398200495b23874f4593e6b827b677704653f01b","slug":"notebooks.fourier-spectral-analysis-tutorial","location":"/notebooks/04.fourier_spectral_analysis_tutorial.ipynb","dependencies":[],"frontmatter":{"title":"Fourier Power Spectrum and Spectral Filtering","content_includes_title":false,"kernelspec":{"name":"python3","display_name":"cookbook-dev","language":"python"},"authors":[{"nameParsed":{"literal":"Juan Diego Mantilla","given":"Juan Diego","family":"Mantilla"},"name":"Juan Diego Mantilla","orcid":"0009-0009-9886-1928","affiliations":["UAlbany"],"github":"jdmantillaq","id":"contributors-myst-generated-uid-0"},{"nameParsed":{"literal":"Sreedevi Puthiyamadam Vasu","given":"Sreedevi Puthiyamadam","family":"Vasu"},"name":"Sreedevi Puthiyamadam Vasu","orcid":"0000-0002-9142-3476","affiliations":["Florida Institute of Technology"],"github":"sputhiyamadam","id":"contributors-myst-generated-uid-1"},{"nameParsed":{"literal":"Robert R. Ford","given":"Robert R.","family":"Ford"},"name":"Robert R. Ford","orcid":"0000-0001-5483-4965","affiliations":["UAlbany"],"github":"r-ford","id":"contributors-myst-generated-uid-2"},{"nameParsed":{"literal":"Suyue Li","given":"Suyue","family":"Li"},"name":"Suyue Li","affiliations":["Texas A&M University"],"github":"suyueli42","id":"contributors-myst-generated-uid-3"},{"nameParsed":{"literal":"Alex Blackmer","given":"Alex","family":"Blackmer"},"name":"Alex Blackmer","orcid":"0009-0001-9889-1870","affiliations":["UAlbany"],"github":"alexblackmer","id":"contributors-myst-generated-uid-4"},{"nameParsed":{"literal":"Yiqun Tian","given":"Yiqun","family":"Tian"},"name":"Yiqun Tian","orcid":"0000-0002-7766-5137","affiliations":["Duke University"],"github":"tianyiqun997","id":"contributors-myst-generated-uid-5"},{"nameParsed":{"literal":"Arman Oliazadeh","given":"Arman","family":"Oliazadeh"},"name":"Arman Oliazadeh","orcid":"0000-0002-3673-9793","affiliations":["University of Georgia"],"github":"Arri2424","id":"contributors-myst-generated-uid-6"}],"open_access":true,"license":{"content":{"id":"CC-BY-4.0","url":"https://creativecommons.org/licenses/by/4.0/","name":"Creative Commons Attribution 4.0 International","free":true,"CC":true},"code":{"id":"Apache-2.0","url":"https://opensource.org/licenses/Apache-2.0","name":"Apache License 2.0","free":true,"osi":true}},"copyright":"2026","affiliations":[{"id":"UAlbany","name":"University at Albany (SUNY)","department":"Atmospheric and Environmental Sciences","url":"https://www.albany.edu/daes"},{"id":"Florida Institute of Technology","name":"Florida Institute of Technology"},{"id":"Texas A&M University","name":"Texas A&M University"},{"id":"Duke University","name":"Duke University"},{"id":"University of Georgia","name":"University of Georgia"},{"id":"CISL","name":"NSF National Center for Atmospheric Research","department":"Computational and Information Systems Lab","url":"https://www.cisl.ucar.edu"},{"id":"Unidata","name":"NSF Unidata","url":"https://www.unidata.ucar.edu"},{"id":"Argonne","name":"Argonne National Laboratory","department":"Environmental Science Division","url":"https://www.anl.gov/evs"},{"id":"CarbonPlan","name":"CarbonPlan","url":"https://carbonplan.org"},{"id":"NVIDIA","name":"NVIDIA Corporation","url":"https://www.nvidia.com/"}],"numbering":{"title":{"offset":1}},"exports":[{"format":"ipynb","filename":"04.fourier_spectral_analysis_tutorial.ipynb","url":"/spectral-analysis-cookbook/_preview/42/build/04.fourier_spectral_-829b1b76d30ec6b99f79c92883c540a6.ipynb"}]},"widgets":{},"mdast":{"type":"root","children":[{"type":"block","kind":"notebook-content","children":[{"type":"thematicBreak","position":{"start":{"line":1,"column":1},"end":{"line":1,"column":1}},"key":"Lb4fVwptXP"}],"key":"da7VvoYTAb"},{"type":"block","kind":"notebook-content","children":[{"type":"heading","depth":2,"position":{"start":{"line":1,"column":1},"end":{"line":1,"column":1}},"children":[{"type":"text","value":"Overview","position":{"start":{"line":1,"column":1},"end":{"line":1,"column":1}},"key":"pTlWxAoGGn"}],"identifier":"overview","label":"Overview","html_id":"overview","implicit":true,"key":"YQloEJRnSv"},{"type":"paragraph","position":{"start":{"line":3,"column":1},"end":{"line":3,"column":1}},"children":[{"type":"text","value":"The ","position":{"start":{"line":3,"column":1},"end":{"line":3,"column":1}},"key":"qx2lbnsNMP"},{"type":"strong","position":{"start":{"line":3,"column":1},"end":{"line":3,"column":1}},"children":[{"type":"text","value":"Fourier transform","position":{"start":{"line":3,"column":1},"end":{"line":3,"column":1}},"key":"ThEQlxGbpF"}],"key":"uxzJpGcGLR"},{"type":"text","value":" decomposes a time series into sine and cosine waves at different frequencies. The ","position":{"start":{"line":3,"column":1},"end":{"line":3,"column":1}},"key":"PxnWXEimhY"},{"type":"strong","position":{"start":{"line":3,"column":1},"end":{"line":3,"column":1}},"children":[{"type":"text","value":"power spectrum","position":{"start":{"line":3,"column":1},"end":{"line":3,"column":1}},"key":"nvzJGxmsGm"}],"key":"qsKFD7fhJT"},{"type":"text","value":" shows how much variance each frequency explains, useful for spotting the annual cycle, intraseasonal variability, and other climate signals.","position":{"start":{"line":3,"column":1},"end":{"line":3,"column":1}},"key":"ER7QPBA76p"}],"key":"W1faJsLqWJ"},{"type":"paragraph","position":{"start":{"line":5,"column":1},"end":{"line":5,"column":1}},"children":[{"type":"text","value":"In this notebook we:","position":{"start":{"line":5,"column":1},"end":{"line":5,"column":1}},"key":"yce3MqCq8L"}],"key":"fuDB9ydML6"},{"type":"list","ordered":true,"start":1,"spread":false,"position":{"start":{"line":7,"column":1},"end":{"line":9,"column":1}},"children":[{"type":"listItem","spread":true,"position":{"start":{"line":7,"column":1},"end":{"line":7,"column":1}},"children":[{"type":"paragraph","children":[{"type":"text","value":"Load daily OLR at a single grid point.","position":{"start":{"line":7,"column":1},"end":{"line":7,"column":1}},"key":"JaSTEEjQ0x"}],"key":"QxzvurYIkR"}],"key":"J6RCbDJeI9"},{"type":"listItem","spread":true,"position":{"start":{"line":8,"column":1},"end":{"line":8,"column":1}},"children":[{"type":"paragraph","children":[{"type":"text","value":"Compute and interpret the ","position":{"start":{"line":8,"column":1},"end":{"line":8,"column":1}},"key":"fOYIejsCG6"},{"type":"strong","position":{"start":{"line":8,"column":1},"end":{"line":8,"column":1}},"children":[{"type":"text","value":"power spectrum","position":{"start":{"line":8,"column":1},"end":{"line":8,"column":1}},"key":"NC5WE8N0l2"}],"key":"B4Oai7qflp"},{"type":"text","value":" of that pixel time series.","position":{"start":{"line":8,"column":1},"end":{"line":8,"column":1}},"key":"Hx8OZYcZZq"}],"key":"ZWUbrNC9VH"}],"key":"vxz1cX7FGd"},{"type":"listItem","spread":true,"position":{"start":{"line":9,"column":1},"end":{"line":9,"column":1}},"children":[{"type":"paragraph","children":[{"type":"text","value":"Apply ","position":{"start":{"line":9,"column":1},"end":{"line":9,"column":1}},"key":"fvC2wzyTuw"},{"type":"strong","position":{"start":{"line":9,"column":1},"end":{"line":9,"column":1}},"children":[{"type":"text","value":"low-pass, high-pass, and band-pass","position":{"start":{"line":9,"column":1},"end":{"line":9,"column":1}},"key":"Xt9DKT0zqs"}],"key":"Xg9oNiSIgP"},{"type":"text","value":" filters in frequency space.","position":{"start":{"line":9,"column":1},"end":{"line":9,"column":1}},"key":"z4Sj8a3fnr"}],"key":"nOhX36YZwL"}],"key":"NlX9MKtHMv"}],"key":"KZSxmshN5t"}],"key":"vSOXU31ESH"},{"type":"block","kind":"notebook-content","children":[{"type":"heading","depth":2,"position":{"start":{"line":1,"column":1},"end":{"line":1,"column":1}},"children":[{"type":"text","value":"Prerequisites","position":{"start":{"line":1,"column":1},"end":{"line":1,"column":1}},"key":"HYJgbmDkx4"}],"identifier":"prerequisites","label":"Prerequisites","html_id":"prerequisites","implicit":true,"key":"orrOl8RKQq"},{"type":"table","position":{"start":{"line":3,"column":1},"end":{"line":6,"column":1}},"children":[{"type":"tableRow","position":{"start":{"line":3,"column":1},"end":{"line":3,"column":1}},"children":[{"type":"tableCell","header":true,"position":{"start":{"line":3,"column":1},"end":{"line":3,"column":1}},"children":[{"type":"text","value":"Concepts","position":{"start":{"line":3,"column":1},"end":{"line":3,"column":1}},"key":"M8kKTvvckW"}],"key":"R20Zbhu2sj"},{"type":"tableCell","header":true,"position":{"start":{"line":3,"column":1},"end":{"line":3,"column":1}},"children":[{"type":"text","value":"Importance","position":{"start":{"line":3,"column":1},"end":{"line":3,"column":1}},"key":"Z6Sb4WXghN"}],"key":"plm2MQ1Tvs"},{"type":"tableCell","header":true,"position":{"start":{"line":3,"column":1},"end":{"line":3,"column":1}},"children":[{"type":"text","value":"Notes","position":{"start":{"line":3,"column":1},"end":{"line":3,"column":1}},"key":"LKtdbIR0m9"}],"key":"M0flD9G5Pb"}],"key":"N1khtOxJZ7"},{"type":"tableRow","position":{"start":{"line":5,"column":1},"end":{"line":5,"column":1}},"children":[{"type":"tableCell","position":{"start":{"line":5,"column":1},"end":{"line":5,"column":1}},"children":[{"type":"link","url":"/notebooks/harmonic-anomalies","position":{"start":{"line":5,"column":1},"end":{"line":5,"column":1}},"children":[{"type":"text","value":"Remove the seasonal cycle using harmonic regression","position":{"start":{"line":5,"column":1},"end":{"line":5,"column":1}},"key":"wlgof1bVQ1"}],"urlSource":"./02.harmonic_anomalies.ipynb","dataUrl":"/notebooks.harmonic-anomalies.json","internal":true,"protocol":"file","key":"PiHZSNfzsf"}],"key":"RSpRILBD9i"},{"type":"tableCell","position":{"start":{"line":5,"column":1},"end":{"line":5,"column":1}},"children":[{"type":"text","value":"Helpful","position":{"start":{"line":5,"column":1},"end":{"line":5,"column":1}},"key":"pXuKydifSn"}],"key":"clfexVFlbe"},{"type":"tableCell","position":{"start":{"line":5,"column":1},"end":{"line":5,"column":1}},"children":[{"type":"text","value":"Same OLR dataset and pixel-selection workflow","position":{"start":{"line":5,"column":1},"end":{"line":5,"column":1}},"key":"PyVliFqIrY"}],"key":"kaj7qUdBBW"}],"key":"FFD3QdctyA"},{"type":"tableRow","position":{"start":{"line":6,"column":1},"end":{"line":6,"column":1}},"children":[{"type":"tableCell","position":{"start":{"line":6,"column":1},"end":{"line":6,"column":1}},"children":[{"type":"link","url":"/notebooks/discrete-fourier-transform","position":{"start":{"line":6,"column":1},"end":{"line":6,"column":1}},"children":[{"type":"text","value":"Discrete Fourier transform","position":{"start":{"line":6,"column":1},"end":{"line":6,"column":1}},"key":"YXZLMK5IV5"}],"urlSource":"./03.discrete_fourier_transform.ipynb","dataUrl":"/notebooks.discrete-fourier-transform.json","internal":true,"protocol":"file","key":"Zmk1nygJZj"}],"key":"YnS2KafI8d"},{"type":"tableCell","position":{"start":{"line":6,"column":1},"end":{"line":6,"column":1}},"children":[{"type":"text","value":"Necessary","position":{"start":{"line":6,"column":1},"end":{"line":6,"column":1}},"key":"yFOLREKEFJ"}],"key":"B5bdBkTJwe"},{"type":"tableCell","position":{"start":{"line":6,"column":1},"end":{"line":6,"column":1}},"children":[{"type":"text","value":"Amplitude, frequency, and period","position":{"start":{"line":6,"column":1},"end":{"line":6,"column":1}},"key":"uYFrVEED5G"}],"key":"RU6e2YFZzV"}],"key":"pnbQ3iheje"}],"key":"dawcOkm6I8"},{"type":"list","ordered":false,"spread":false,"position":{"start":{"line":8,"column":1},"end":{"line":8,"column":1}},"children":[{"type":"listItem","spread":true,"position":{"start":{"line":8,"column":1},"end":{"line":8,"column":1}},"children":[{"type":"paragraph","children":[{"type":"strong","position":{"start":{"line":8,"column":1},"end":{"line":8,"column":1}},"children":[{"type":"text","value":"Time to learn","position":{"start":{"line":8,"column":1},"end":{"line":8,"column":1}},"key":"NUbCDTF1PQ"}],"key":"HOlFoDjUuy"},{"type":"text","value":": ~25 minutes","position":{"start":{"line":8,"column":1},"end":{"line":8,"column":1}},"key":"esg98XPPoU"}],"key":"coXLrQKPam"}],"key":"GWWpW4jLf2"}],"key":"uTLZbVhIIK"}],"key":"jJZmDabV52"},{"type":"block","kind":"notebook-content","children":[{"type":"thematicBreak","position":{"start":{"line":1,"column":1},"end":{"line":1,"column":1}},"key":"ftp1UNHAjX"}],"key":"LANi7lFXag"},{"type":"block","kind":"notebook-content","children":[{"type":"heading","depth":2,"position":{"start":{"line":1,"column":1},"end":{"line":1,"column":1}},"children":[{"type":"text","value":"Imports","position":{"start":{"line":1,"column":1},"end":{"line":1,"column":1}},"key":"Xgpm4R7dqq"}],"identifier":"imports","label":"Imports","html_id":"imports","implicit":true,"key":"TgWh4Pr6z6"},{"type":"paragraph","position":{"start":{"line":3,"column":1},"end":{"line":3,"column":1}},"children":[{"type":"text","value":"All packages are imported up front. ","position":{"start":{"line":3,"column":1},"end":{"line":3,"column":1}},"key":"RGDdzlngI6"},{"type":"inlineCode","value":"s3fs","position":{"start":{"line":3,"column":1},"end":{"line":3,"column":1}},"key":"KVNNxhOZAV"},{"type":"text","value":" reads anonymously from the public Pythia bucket on the Jetstream2 S3 endpoint.","position":{"start":{"line":3,"column":1},"end":{"line":3,"column":1}},"key":"NUkR8PE3dK"}],"key":"kdg6ghJQTG"}],"key":"nmyPvRGf3W"},{"type":"block","kind":"notebook-code","children":[{"type":"code","lang":"python","executable":true,"value":"import numpy as np\nimport pandas as pd\nimport matplotlib.pyplot as plt\nimport seaborn as sns\n\nimport s3fs\nimport xarray as xr\n\nsns.set_theme(style=\"whitegrid\", context=\"notebook\", font_scale=1.2)\n\nURL = \"https://js2.jetstream-cloud.org:8001/\"\nfs = s3fs.S3FileSystem(anon=True, client_kwargs=dict(endpoint_url=URL))","key":"nN02snig7X"},{"type":"outputs","id":"q5ci0_97_PhzUFG3sVJud","children":[],"key":"ApXcIWDfou"}],"key":"w4rnAVws6C"},{"type":"block","kind":"notebook-content","children":[{"type":"heading","depth":2,"position":{"start":{"line":1,"column":1},"end":{"line":1,"column":1}},"children":[{"type":"text","value":"Load NOAA OLR","position":{"start":{"line":1,"column":1},"end":{"line":1,"column":1}},"key":"w2QFlT50eW"}],"identifier":"load-noaa-olr","label":"Load NOAA OLR","html_id":"load-noaa-olr","implicit":true,"key":"gxJK9jYVDI"},{"type":"paragraph","position":{"start":{"line":3,"column":1},"end":{"line":3,"column":1}},"children":[{"type":"text","value":"We use daily ","position":{"start":{"line":3,"column":1},"end":{"line":3,"column":1}},"key":"XzgplwAnbH"},{"type":"strong","position":{"start":{"line":3,"column":1},"end":{"line":3,"column":1}},"children":[{"type":"text","value":"Outgoing Longwave Radiation (OLR)","position":{"start":{"line":3,"column":1},"end":{"line":3,"column":1}},"key":"VLOArBwOlg"}],"key":"JNp5WwvgAn"},{"type":"text","value":" from NOAA ","position":{"start":{"line":3,"column":1},"end":{"line":3,"column":1}},"key":"wmVD5gbMqj"},{"type":"citeGroup","kind":"parenthetical","position":{"start":{"line":3,"column":1},"end":{"line":3,"column":1}},"children":[{"type":"cite","identifier":"lee2014noaa","label":"lee2014noaa","kind":"parenthetical","position":{"start":{"line":3,"column":63},"end":{"line":3,"column":75}},"children":[{"type":"text","value":"Lee & others, 2014","key":"KtBAtJzgzF"}],"enumerator":"1","key":"tImpfnXc9T"}],"key":"mS1uDCzkVX"},{"type":"text","value":", stored as a Zarr dataset on the Pythia Jetstream2 bucket, the same source as in ","position":{"start":{"line":3,"column":1},"end":{"line":3,"column":1}},"key":"ReVjYhXkvj"},{"type":"link","url":"./harmonic_anomalies.ipynb","position":{"start":{"line":3,"column":1},"end":{"line":3,"column":1}},"children":[{"type":"text","value":"harmonic anomalies","position":{"start":{"line":3,"column":1},"end":{"line":3,"column":1}},"key":"SRKFYjXnes"}],"urlSource":"./harmonic_anomalies.ipynb","key":"aZfafGuqI7"},{"type":"text","value":".","position":{"start":{"line":3,"column":1},"end":{"line":3,"column":1}},"key":"nM1Ofb5qrI"}],"key":"sbxT6PIJpY"}],"key":"VLXzUYldXZ"},{"type":"block","kind":"notebook-code","children":[{"type":"code","lang":"python","executable":true,"value":"olr_noaa_store = s3fs.S3Map(\n    root=\"pythia/olr_noaa.zarr\",\n    s3=fs,\n    check=False,\n)\n\nolr_noaa = xr.open_zarr(olr_noaa_store)\nolr_noaa = olr_noaa.rename_vars({\"__xarray_dataarray_variable__\": \"olr\"})\nolr_noaa = olr_noaa.chunk({\"time\": -1})\nolr_noaa = olr_noaa.interpolate_na(dim=\"time\", method=\"linear\")","key":"i9PoSDCHbv"},{"type":"outputs","id":"cPouCDgnduFD9IOdLDmUg","children":[],"key":"auo1vXxljH"}],"key":"btifcPYV20"},{"type":"block","kind":"notebook-content","children":[{"type":"heading","depth":2,"position":{"start":{"line":1,"column":1},"end":{"line":1,"column":1}},"children":[{"type":"text","value":"Select a single-pixel time series","position":{"start":{"line":1,"column":1},"end":{"line":1,"column":1}},"key":"XBiOViqHb5"}],"identifier":"select-a-single-pixel-time-series","label":"Select a single-pixel time series","html_id":"select-a-single-pixel-time-series","implicit":true,"key":"dcPnicX9YP"},{"type":"paragraph","position":{"start":{"line":3,"column":1},"end":{"line":3,"column":1}},"children":[{"type":"text","value":"Spectral analysis starts with one location. We pick a tropical grid point and remove the time mean so the FFT focuses on variability rather than the absolute OLR level.","position":{"start":{"line":3,"column":1},"end":{"line":3,"column":1}},"key":"iDOjLTwqPj"}],"key":"qxHw1aqXy2"}],"key":"FOA6mSjzjn"},{"type":"block","kind":"notebook-code","children":[{"type":"code","lang":"python","executable":true,"value":"lat_select = 20\nlon_select = 50\n\nolr_series = olr_noaa[\"olr\"].sel(\n    lat=lat_select, lon=lon_select, method=\"nearest\"\n)\nseries = olr_series.values\nseries_centered = series - series.mean()\nn_time = len(series)\n\nfig, ax = plt.subplots(figsize=(8, 3))\nolr_series.plot(ax=ax, color=\"C0\", linewidth=0.8)\nax.set_title(f\"Daily OLR at (lat={lat_select}, lon={lon_select})\")\nax.set_ylabel(\"OLR (W/m$^2$)\")\nplt.show()","key":"g9EcIGl4ff"},{"type":"outputs","id":"YxrQ0PjPOPq_iy68G7I-H","children":[{"type":"output","children":[],"jupyter_data":{"output_type":"display_data","metadata":{},"data":{"text/plain":{"content":"<Figure size 800x300 with 1 Axes>","content_type":"text/plain"},"image/png":{"content_type":"image/png","hash":"48249540be8e16b343b43bf6303a6193","path":"/spectral-analysis-cookbook/_preview/42/build/48249540be8e16b343b43bf6303a6193.png"}}},"key":"fB6JPXalkx"}],"key":"yBYeospZ5I"}],"key":"yuv4Bh51ly"},{"type":"block","kind":"notebook-content","children":[{"type":"heading","depth":2,"position":{"start":{"line":1,"column":1},"end":{"line":1,"column":1}},"children":[{"type":"text","value":"Compute the power spectrum","position":{"start":{"line":1,"column":1},"end":{"line":1,"column":1}},"key":"Y6GUcieBaP"}],"identifier":"compute-the-power-spectrum","label":"Compute the power spectrum","html_id":"compute-the-power-spectrum","implicit":true,"key":"AIP8P5hndo"},{"type":"paragraph","position":{"start":{"line":3,"column":1},"end":{"line":3,"column":1}},"children":[{"type":"text","value":"For a centered series ","position":{"start":{"line":3,"column":1},"end":{"line":3,"column":1}},"key":"KDLdoh9Z87"},{"type":"inlineMath","value":"x(t)","position":{"start":{"line":3,"column":1},"end":{"line":3,"column":1}},"html":"<span class=\"katex\"><span class=\"katex-mathml\"><math xmlns=\"http://www.w3.org/1998/Math/MathML\"><semantics><mrow><mi>x</mi><mo stretchy=\"false\">(</mo><mi>t</mi><mo stretchy=\"false\">)</mo></mrow><annotation encoding=\"application/x-tex\">x(t)</annotation></semantics></math></span><span class=\"katex-html\" aria-hidden=\"true\"><span class=\"base\"><span class=\"strut\" style=\"height:1em;vertical-align:-0.25em;\"></span><span class=\"mord mathnormal\">x</span><span class=\"mopen\">(</span><span class=\"mord mathnormal\">t</span><span class=\"mclose\">)</span></span></span></span>","key":"LPicLB2lZD"},{"type":"text","value":" with sampling interval ","position":{"start":{"line":3,"column":1},"end":{"line":3,"column":1}},"key":"anFAKuFbji"},{"type":"inlineMath","value":"\\Delta t = 1","position":{"start":{"line":3,"column":1},"end":{"line":3,"column":1}},"html":"<span class=\"katex\"><span class=\"katex-mathml\"><math xmlns=\"http://www.w3.org/1998/Math/MathML\"><semantics><mrow><mi mathvariant=\"normal\">Δ</mi><mi>t</mi><mo>=</mo><mn>1</mn></mrow><annotation encoding=\"application/x-tex\">\\Delta t = 1</annotation></semantics></math></span><span class=\"katex-html\" aria-hidden=\"true\"><span class=\"base\"><span class=\"strut\" style=\"height:0.6833em;\"></span><span class=\"mord\">Δ</span><span class=\"mord mathnormal\">t</span><span class=\"mspace\" style=\"margin-right:0.2778em;\"></span><span class=\"mrel\">=</span><span class=\"mspace\" style=\"margin-right:0.2778em;\"></span></span><span class=\"base\"><span class=\"strut\" style=\"height:0.6444em;\"></span><span class=\"mord\">1</span></span></span></span>","key":"bLaEVyUMv6"},{"type":"text","value":" day, the discrete Fourier transform gives complex coefficients ","position":{"start":{"line":3,"column":1},"end":{"line":3,"column":1}},"key":"wjDQl2DejI"},{"type":"inlineMath","value":"\\hat{x}_k","position":{"start":{"line":3,"column":1},"end":{"line":3,"column":1}},"html":"<span class=\"katex\"><span class=\"katex-mathml\"><math xmlns=\"http://www.w3.org/1998/Math/MathML\"><semantics><mrow><msub><mover accent=\"true\"><mi>x</mi><mo>^</mo></mover><mi>k</mi></msub></mrow><annotation encoding=\"application/x-tex\">\\hat{x}_k</annotation></semantics></math></span><span class=\"katex-html\" aria-hidden=\"true\"><span class=\"base\"><span class=\"strut\" style=\"height:0.8444em;vertical-align:-0.15em;\"></span><span class=\"mord\"><span class=\"mord accent\"><span class=\"vlist-t\"><span class=\"vlist-r\"><span class=\"vlist\" style=\"height:0.6944em;\"><span style=\"top:-3em;\"><span class=\"pstrut\" style=\"height:3em;\"></span><span class=\"mord mathnormal\">x</span></span><span style=\"top:-3em;\"><span class=\"pstrut\" style=\"height:3em;\"></span><span class=\"accent-body\" style=\"left:-0.2222em;\"><span class=\"mord\">^</span></span></span></span></span></span></span><span class=\"msupsub\"><span class=\"vlist-t vlist-t2\"><span class=\"vlist-r\"><span class=\"vlist\" style=\"height:0.3361em;\"><span style=\"top:-2.55em;margin-left:0em;margin-right:0.05em;\"><span class=\"pstrut\" style=\"height:2.7em;\"></span><span class=\"sizing reset-size6 size3 mtight\"><span class=\"mord mathnormal mtight\" style=\"margin-right:0.03148em;\">k</span></span></span></span><span class=\"vlist-s\">​</span></span><span class=\"vlist-r\"><span class=\"vlist\" style=\"height:0.15em;\"><span></span></span></span></span></span></span></span></span></span>","key":"aRjkqb9KmY"},{"type":"text","value":". The ","position":{"start":{"line":3,"column":1},"end":{"line":3,"column":1}},"key":"siZ3qUO2IN"},{"type":"strong","position":{"start":{"line":3,"column":1},"end":{"line":3,"column":1}},"children":[{"type":"text","value":"power","position":{"start":{"line":3,"column":1},"end":{"line":3,"column":1}},"key":"MFyvHp8LtT"}],"key":"wMQaTfvGhF"},{"type":"text","value":" at frequency ","position":{"start":{"line":3,"column":1},"end":{"line":3,"column":1}},"key":"bbzlVdZ9Gl"},{"type":"inlineMath","value":"k","position":{"start":{"line":3,"column":1},"end":{"line":3,"column":1}},"html":"<span class=\"katex\"><span class=\"katex-mathml\"><math xmlns=\"http://www.w3.org/1998/Math/MathML\"><semantics><mrow><mi>k</mi></mrow><annotation encoding=\"application/x-tex\">k</annotation></semantics></math></span><span class=\"katex-html\" aria-hidden=\"true\"><span class=\"base\"><span class=\"strut\" style=\"height:0.6944em;\"></span><span class=\"mord mathnormal\" style=\"margin-right:0.03148em;\">k</span></span></span></span>","key":"r9irYcRFIj"},{"type":"text","value":" is ","position":{"start":{"line":3,"column":1},"end":{"line":3,"column":1}},"key":"mTRz9LzBGK"},{"type":"inlineMath","value":"|\\hat{x}_k|^2","position":{"start":{"line":3,"column":1},"end":{"line":3,"column":1}},"html":"<span class=\"katex\"><span class=\"katex-mathml\"><math xmlns=\"http://www.w3.org/1998/Math/MathML\"><semantics><mrow><mi mathvariant=\"normal\">∣</mi><msub><mover accent=\"true\"><mi>x</mi><mo>^</mo></mover><mi>k</mi></msub><msup><mi mathvariant=\"normal\">∣</mi><mn>2</mn></msup></mrow><annotation encoding=\"application/x-tex\">|\\hat{x}_k|^2</annotation></semantics></math></span><span class=\"katex-html\" aria-hidden=\"true\"><span class=\"base\"><span class=\"strut\" style=\"height:1.0641em;vertical-align:-0.25em;\"></span><span class=\"mord\">∣</span><span class=\"mord\"><span class=\"mord accent\"><span class=\"vlist-t\"><span class=\"vlist-r\"><span class=\"vlist\" style=\"height:0.6944em;\"><span style=\"top:-3em;\"><span class=\"pstrut\" style=\"height:3em;\"></span><span class=\"mord mathnormal\">x</span></span><span style=\"top:-3em;\"><span class=\"pstrut\" style=\"height:3em;\"></span><span class=\"accent-body\" style=\"left:-0.2222em;\"><span class=\"mord\">^</span></span></span></span></span></span></span><span class=\"msupsub\"><span class=\"vlist-t vlist-t2\"><span class=\"vlist-r\"><span class=\"vlist\" style=\"height:0.3361em;\"><span style=\"top:-2.55em;margin-left:0em;margin-right:0.05em;\"><span class=\"pstrut\" style=\"height:2.7em;\"></span><span class=\"sizing reset-size6 size3 mtight\"><span class=\"mord mathnormal mtight\" style=\"margin-right:0.03148em;\">k</span></span></span></span><span class=\"vlist-s\">​</span></span><span class=\"vlist-r\"><span class=\"vlist\" style=\"height:0.15em;\"><span></span></span></span></span></span></span><span class=\"mord\"><span class=\"mord\">∣</span><span class=\"msupsub\"><span class=\"vlist-t\"><span class=\"vlist-r\"><span class=\"vlist\" style=\"height:0.8141em;\"><span style=\"top:-3.063em;margin-right:0.05em;\"><span class=\"pstrut\" style=\"height:2.7em;\"></span><span class=\"sizing reset-size6 size3 mtight\"><span class=\"mord mtight\">2</span></span></span></span></span></span></span></span></span></span></span>","key":"uNxrdxS9YZ"},{"type":"text","value":". Summing power across all frequencies equals the series variance.","position":{"start":{"line":3,"column":1},"end":{"line":3,"column":1}},"key":"S2WgnsVsWM"}],"key":"stANl1Wl7R"},{"type":"paragraph","position":{"start":{"line":5,"column":1},"end":{"line":5,"column":1}},"children":[{"type":"text","value":"We convert frequency to ","position":{"start":{"line":5,"column":1},"end":{"line":5,"column":1}},"key":"EdKsPOJq9h"},{"type":"strong","position":{"start":{"line":5,"column":1},"end":{"line":5,"column":1}},"children":[{"type":"text","value":"period","position":{"start":{"line":5,"column":1},"end":{"line":5,"column":1}},"key":"qmVbp7vg4Z"}],"key":"cN1us7SHJC"},{"type":"text","value":" (days) with ","position":{"start":{"line":5,"column":1},"end":{"line":5,"column":1}},"key":"TdLIxb25pg"},{"type":"inlineMath","value":"\\text{period} = 1 / |f|","position":{"start":{"line":5,"column":1},"end":{"line":5,"column":1}},"html":"<span class=\"katex\"><span class=\"katex-mathml\"><math xmlns=\"http://www.w3.org/1998/Math/MathML\"><semantics><mrow><mtext>period</mtext><mo>=</mo><mn>1</mn><mi mathvariant=\"normal\">/</mi><mi mathvariant=\"normal\">∣</mi><mi>f</mi><mi mathvariant=\"normal\">∣</mi></mrow><annotation encoding=\"application/x-tex\">\\text{period} = 1 / |f|</annotation></semantics></math></span><span class=\"katex-html\" aria-hidden=\"true\"><span class=\"base\"><span class=\"strut\" style=\"height:0.8889em;vertical-align:-0.1944em;\"></span><span class=\"mord text\"><span class=\"mord\">period</span></span><span class=\"mspace\" style=\"margin-right:0.2778em;\"></span><span class=\"mrel\">=</span><span class=\"mspace\" style=\"margin-right:0.2778em;\"></span></span><span class=\"base\"><span class=\"strut\" style=\"height:1em;vertical-align:-0.25em;\"></span><span class=\"mord\">1/∣</span><span class=\"mord mathnormal\" style=\"margin-right:0.10764em;\">f</span><span class=\"mord\">∣</span></span></span></span>","key":"R2BaNvGoZR"},{"type":"text","value":" and express each bin as the ","position":{"start":{"line":5,"column":1},"end":{"line":5,"column":1}},"key":"xOZPfINO63"},{"type":"strong","position":{"start":{"line":5,"column":1},"end":{"line":5,"column":1}},"children":[{"type":"text","value":"fraction of total variance","position":{"start":{"line":5,"column":1},"end":{"line":5,"column":1}},"key":"gWflkLxP0J"}],"key":"HXuInu63Oa"},{"type":"text","value":" it explains. Peaks near 365 days mark the annual cycle and its harmonics.","position":{"start":{"line":5,"column":1},"end":{"line":5,"column":1}},"key":"NL0FSsE9D3"}],"key":"vhjqVEHMsf"}],"key":"jgvSEcPo1g"},{"type":"block","kind":"notebook-code","children":[{"type":"code","lang":"python","executable":true,"value":"def power_spectrum(series, dt=1.0):\n    \"\"\"Return positive-frequency periods (days) and explained variance (%).\"\"\"\n    x = series - np.mean(series)\n    n = len(x)\n    freqs = np.fft.rfftfreq(n, d=dt)\n    coeffs = np.fft.rfft(x)\n    power = np.abs(coeffs) ** 2\n\n    var = np.var(x)\n    pct_var = 100.0 * power / power.sum() if power.sum() > 0 else power\n\n    with np.errstate(divide=\"ignore\"):\n        periods = np.where(freqs > 0, 1.0 / freqs, np.inf)\n\n    mask = freqs > 0\n    return periods[mask], pct_var[mask], var\n\n\nperiods, pct_var, series_var = power_spectrum(series)\nprint(f\"Series length: {n_time} days | variance: {series_var:.2f} (W/m$^2$)$^2$\")","key":"vX4SauxqVX"},{"type":"outputs","id":"KD88aj4g7TY3Dwr0hAoER","children":[{"type":"output","children":[],"jupyter_data":{"output_type":"stream","name":"stdout","text":"Series length: 16802 days | variance: 492.19 (W/m$^2$)$^2$\n"},"key":"Akeux529S9"}],"key":"KcbP6cG65e"}],"key":"q6eGewrx8y"},{"type":"block","kind":"notebook-code","children":[{"type":"code","lang":"python","executable":true,"value":"fig, ax = plt.subplots(figsize=(6, 4))\nax.plot(periods, pct_var, color=\"k\", linewidth=1.6)\nax.set_xscale(\"log\")\nax.set_xlim(10, n_time)\nax.set_xlabel(\"Period (days)\")\nax.set_ylabel(\"Explained variance (%)\")\nax.set_title(\"Power spectrum of a single OLR pixel\")\n\nfor period, label, color in [\n    (365.25, \"1 year\", \"C3\"),\n    (365.25 / 2, \"6 months\", \"C4\"),\n    (365.25 / 3, \"4 months\", \"C5\"),\n    (365.25 / 4, \"3 months\", \"C6\"),\n]:\n    ax.axvline(period, color=color, linestyle=\"--\", alpha=0.8, label=label, zorder=1)\nax.legend(loc=\"upper right\")\nplt.show()","key":"KEjvK9R1SH"},{"type":"outputs","id":"vimiGCPNE-SIMlG9YDmOi","children":[{"type":"output","children":[],"jupyter_data":{"output_type":"display_data","metadata":{},"data":{"text/plain":{"content":"<Figure size 600x400 with 1 Axes>","content_type":"text/plain"},"image/png":{"content_type":"image/png","hash":"2ccd4143fa68e59f77230017a4a66ee8","path":"/spectral-analysis-cookbook/_preview/42/build/2ccd4143fa68e59f77230017a4a66ee8.png"}}},"key":"ytWz9WlFoZ"}],"key":"XpOjxNqmyy"}],"key":"VvqmKhg7Gw"},{"type":"block","kind":"notebook-content","children":[{"type":"paragraph","position":{"start":{"line":1,"column":1},"end":{"line":1,"column":1}},"children":[{"type":"text","value":"As we see, the largest peaks usually occur near the ","position":{"start":{"line":1,"column":1},"end":{"line":1,"column":1}},"key":"iSYCt8PRkc"},{"type":"strong","position":{"start":{"line":1,"column":1},"end":{"line":1,"column":1}},"children":[{"type":"text","value":"annual cycle","position":{"start":{"line":1,"column":1},"end":{"line":1,"column":1}},"key":"entOPkNY8k"}],"key":"flBwQZMLO7"},{"type":"text","value":" and its harmonics. While this confirms that the seasonal cycle is the dominant source of variability, it offers little new insight, as this behavior is already well known.","position":{"start":{"line":1,"column":1},"end":{"line":1,"column":1}},"key":"Qt3cKGim6e"}],"key":"Wt8ZioaupE"},{"type":"paragraph","position":{"start":{"line":3,"column":1},"end":{"line":3,"column":1}},"children":[{"type":"text","value":"To reveal variability beyond the seasonal cycle, we repeat the analysis using anomalies obtained after removing the annual cycle and its first four harmonics, following the procedure described in ","position":{"start":{"line":3,"column":1},"end":{"line":3,"column":1}},"key":"ta3F1TuPko"},{"type":"link","url":"/notebooks/harmonic-anomalies","position":{"start":{"line":3,"column":1},"end":{"line":3,"column":1}},"children":[{"type":"text","value":"Remove the seasonal cycle using harmonic regression","position":{"start":{"line":3,"column":1},"end":{"line":3,"column":1}},"key":"LUnHlvYLR6"}],"urlSource":"./02.harmonic_anomalies.ipynb","dataUrl":"/notebooks.harmonic-anomalies.json","internal":true,"protocol":"file","key":"I5DRQosSGR"},{"type":"text","value":". This filtering suppresses the seasonal signal, allowing other modes of variability to emerge more clearly.","position":{"start":{"line":3,"column":1},"end":{"line":3,"column":1}},"key":"iOmlEoOBAO"}],"key":"BRiFduPKR9"}],"key":"bnP3vgZEEf"},{"type":"block","kind":"notebook-code","children":[{"type":"code","lang":"python","executable":true,"value":"n_harmonics = 4\nyear_period = 365.25  # days\n\nt = np.arange(n_time)\nX = np.ones((n_time, 2 * n_harmonics + 1))\nfor i in range(1, n_harmonics + 1):\n    X[:, 2 * i - 1] = np.sin(i * 2 * np.pi * t / year_period)\n    X[:, 2 * i] = np.cos(i * 2 * np.pi * t / year_period)\n\n\ncoeffs = np.linalg.lstsq(X, series, rcond=None)[0]\nannual_cycle = X @ coeffs\nanomalies = series - annual_cycle\n\nperiods, pct_var_harmonics, series_var_harmonics = power_spectrum(anomalies)\n","key":"MsdNBrG7bn"},{"type":"outputs","id":"pPil78tY5Ayw-LRtqruey","children":[],"key":"FdGkplFYbs"}],"key":"ND5D67xJ9t"},{"type":"block","kind":"notebook-code","children":[{"type":"code","lang":"python","executable":true,"value":"fig, ax = plt.subplots(figsize=(6, 4))\nax.plot(periods, pct_var_harmonics, color=\"k\", linewidth=1.6)\nax.set_xscale(\"log\")\nax.set_xlim(2, n_time)\nax.set_xlabel(\"Period (days)\")\nax.set_ylabel(\"Explained variance (%)\")\nax.set_title(\"Power spectrum of a single OLR pixel\")\n\nfor period, label, color in [\n    (365.25, \"1 year\", \"C3\"),\n    (365.25 / 2, \"6 months\", \"C4\"),\n    (365.25 / 3, \"4 months\", \"C5\"),\n    (365.25 / 4, \"3 months\", \"C6\"),\n]:\n    ax.axvline(period, color=color, linestyle=\"--\", alpha=0.8, label=label, zorder=1)\nax.legend(loc=\"upper right\")\nplt.show()","key":"kRhzxgpUT9"},{"type":"outputs","id":"kIMFzH9pj-poM6ZLYZjYR","children":[{"type":"output","children":[],"jupyter_data":{"output_type":"display_data","metadata":{},"data":{"text/plain":{"content":"<Figure size 600x400 with 1 Axes>","content_type":"text/plain"},"image/png":{"content_type":"image/png","hash":"6d0f9260f334ae90cd100bf4c9f6e33e","path":"/spectral-analysis-cookbook/_preview/42/build/6d0f9260f334ae90cd100bf4c9f6e33e.png"}}},"key":"lUdFnTtIbn"}],"key":"whOB0GKXmg"}],"key":"S2t4xT1dVo"},{"type":"block","kind":"notebook-content","children":[{"type":"paragraph","position":{"start":{"line":1,"column":1},"end":{"line":1,"column":1}},"children":[{"type":"text","value":"Now we see that the largest fraction of the explained variability is concentrated at low frequencies, corresponding to periods longer than ","position":{"start":{"line":1,"column":1},"end":{"line":1,"column":1}},"key":"Zl1p6ScvKb"},{"type":"span","position":{"start":{"line":1,"column":1},"end":{"line":1,"column":1}},"children":[{"type":"text","value":"10","key":"VIYIkvG9as"},{"type":"superscript","children":[{"type":"text","value":"4","key":"zq6M2GMqga"}],"key":"X3y1K2y2fw"}],"key":"TMxIX6VL7k"},{"type":"text","value":" days. A substantial amount of variance is also found in the interannual band (approximately 2–7 years), while another significant contribution arises from intraseasonal variability, with periods between about 20 and 90 days.","position":{"start":{"line":1,"column":1},"end":{"line":1,"column":1}},"key":"AO7aEtUceD"}],"key":"PgSeaSRozL"}],"key":"u0Ws5WKMtR"},{"type":"block","kind":"notebook-content","children":[{"type":"heading","depth":2,"position":{"start":{"line":1,"column":1},"end":{"line":1,"column":1}},"children":[{"type":"text","value":"Spectral filtering","position":{"start":{"line":1,"column":1},"end":{"line":1,"column":1}},"key":"xblZieZqwO"}],"identifier":"spectral-filtering","label":"Spectral filtering","html_id":"spectral-filtering","implicit":true,"key":"l0unykKbAz"},{"type":"paragraph","position":{"start":{"line":3,"column":1},"end":{"line":3,"column":1}},"children":[{"type":"text","value":"Spectral filtering isolates variability within a desired range of time scales by modifying the Fourier coefficients before transforming the signal back to the time domain. The procedure consists of three steps:","position":{"start":{"line":3,"column":1},"end":{"line":3,"column":1}},"key":"HJrx2TDR66"}],"key":"qQhVQlcAHT"},{"type":"list","ordered":true,"start":1,"spread":false,"position":{"start":{"line":5,"column":1},"end":{"line":8,"column":1}},"children":[{"type":"listItem","spread":true,"position":{"start":{"line":5,"column":1},"end":{"line":5,"column":1}},"children":[{"type":"paragraph","children":[{"type":"text","value":"Compute the FFT of the mean-centered time series.","position":{"start":{"line":5,"column":1},"end":{"line":5,"column":1}},"key":"MGjPgbh5Od"}],"key":"ZUA3eFc5Kr"}],"key":"lBBj98A2oc"},{"type":"listItem","spread":true,"position":{"start":{"line":6,"column":1},"end":{"line":6,"column":1}},"children":[{"type":"paragraph","children":[{"type":"text","value":"Retain only the Fourier coefficients corresponding to the desired period range.","position":{"start":{"line":6,"column":1},"end":{"line":6,"column":1}},"key":"ilgREK2YGq"}],"key":"FqflJHUmbs"}],"key":"R2a5aBOlyz"},{"type":"listItem","spread":true,"position":{"start":{"line":7,"column":1},"end":{"line":8,"column":1}},"children":[{"type":"paragraph","children":[{"type":"text","value":"Perform the inverse FFT and add the mean back to reconstruct the filtered signal.","position":{"start":{"line":7,"column":1},"end":{"line":7,"column":1}},"key":"iDBKweBwXq"}],"key":"xUO0cHVdeX"}],"key":"sKW9i7v6YJ"}],"key":"oQ6uKB1nYs"},{"type":"thematicBreak","position":{"start":{"line":9,"column":1},"end":{"line":9,"column":1}},"key":"G7HySXpYT6"},{"type":"table","position":{"start":{"line":11,"column":1},"end":{"line":15,"column":1}},"children":[{"type":"tableRow","position":{"start":{"line":11,"column":1},"end":{"line":11,"column":1}},"children":[{"type":"tableCell","header":true,"position":{"start":{"line":11,"column":1},"end":{"line":11,"column":1}},"children":[{"type":"text","value":"Filter","position":{"start":{"line":11,"column":1},"end":{"line":11,"column":1}},"key":"dOd6gY3ccD"}],"key":"lcbHo8O4cn"},{"type":"tableCell","header":true,"position":{"start":{"line":11,"column":1},"end":{"line":11,"column":1}},"children":[{"type":"text","value":"Keeps periods","position":{"start":{"line":11,"column":1},"end":{"line":11,"column":1}},"key":"O8MeadZgmU"}],"key":"a09zMet8SC"},{"type":"tableCell","header":true,"position":{"start":{"line":11,"column":1},"end":{"line":11,"column":1}},"children":[{"type":"text","value":"Typical use","position":{"start":{"line":11,"column":1},"end":{"line":11,"column":1}},"key":"TVamvNkSj3"}],"key":"Vm66YOuxVE"}],"key":"JA4xW7jWaM"},{"type":"tableRow","position":{"start":{"line":13,"column":1},"end":{"line":13,"column":1}},"children":[{"type":"tableCell","position":{"start":{"line":13,"column":1},"end":{"line":13,"column":1}},"children":[{"type":"strong","position":{"start":{"line":13,"column":1},"end":{"line":13,"column":1}},"children":[{"type":"text","value":"Low-pass","position":{"start":{"line":13,"column":1},"end":{"line":13,"column":1}},"key":"Klp3KH2pWZ"}],"key":"PGrVtEdSuO"}],"key":"v2bLGJTAFW"},{"type":"tableCell","position":{"start":{"line":13,"column":1},"end":{"line":13,"column":1}},"children":[{"type":"text","value":"longer than a cutoff","position":{"start":{"line":13,"column":1},"end":{"line":13,"column":1}},"key":"FHQu4MBhn2"}],"key":"BVwr4awDUQ"},{"type":"tableCell","position":{"start":{"line":13,"column":1},"end":{"line":13,"column":1}},"children":[{"type":"text","value":"isolate slow variability (e.g., interannual to decadal)","position":{"start":{"line":13,"column":1},"end":{"line":13,"column":1}},"key":"OENQkBhJ4y"}],"key":"jlYXWTJM0Y"}],"key":"zVd0qaHEzZ"},{"type":"tableRow","position":{"start":{"line":14,"column":1},"end":{"line":14,"column":1}},"children":[{"type":"tableCell","position":{"start":{"line":14,"column":1},"end":{"line":14,"column":1}},"children":[{"type":"strong","position":{"start":{"line":14,"column":1},"end":{"line":14,"column":1}},"children":[{"type":"text","value":"High-pass","position":{"start":{"line":14,"column":1},"end":{"line":14,"column":1}},"key":"AAQgLra3sP"}],"key":"C5KXI7i0uE"}],"key":"JXrzMJlCb3"},{"type":"tableCell","position":{"start":{"line":14,"column":1},"end":{"line":14,"column":1}},"children":[{"type":"text","value":"shorter than a cutoff","position":{"start":{"line":14,"column":1},"end":{"line":14,"column":1}},"key":"yaWQBegs5G"}],"key":"O9oa86mni4"},{"type":"tableCell","position":{"start":{"line":14,"column":1},"end":{"line":14,"column":1}},"children":[{"type":"text","value":"remove slow variations such as trends and the seasonal cycle","position":{"start":{"line":14,"column":1},"end":{"line":14,"column":1}},"key":"E1Nn3bnSx4"}],"key":"qVpx79Xliu"}],"key":"crqKGRga1z"},{"type":"tableRow","position":{"start":{"line":15,"column":1},"end":{"line":15,"column":1}},"children":[{"type":"tableCell","position":{"start":{"line":15,"column":1},"end":{"line":15,"column":1}},"children":[{"type":"strong","position":{"start":{"line":15,"column":1},"end":{"line":15,"column":1}},"children":[{"type":"text","value":"Band-pass","position":{"start":{"line":15,"column":1},"end":{"line":15,"column":1}},"key":"KusabyBm9Z"}],"key":"HHDrOzWYn8"}],"key":"CXb6OhPSRc"},{"type":"tableCell","position":{"start":{"line":15,"column":1},"end":{"line":15,"column":1}},"children":[{"type":"text","value":"between two cutoffs","position":{"start":{"line":15,"column":1},"end":{"line":15,"column":1}},"key":"glley5352k"}],"key":"M4vcKHLEh8"},{"type":"tableCell","position":{"start":{"line":15,"column":1},"end":{"line":15,"column":1}},"children":[{"type":"text","value":"isolate a specific range of variability (e.g., MJO)","position":{"start":{"line":15,"column":1},"end":{"line":15,"column":1}},"key":"oGAKm0MeYk"}],"key":"ujwWbYseAq"}],"key":"ybtzqOI9Lq"}],"key":"bYkXIBTAlO"},{"type":"paragraph","position":{"start":{"line":17,"column":1},"end":{"line":17,"column":1}},"children":[{"type":"text","value":"The helper function ","position":{"start":{"line":17,"column":1},"end":{"line":17,"column":1}},"key":"akwVujA3EV"},{"type":"inlineCode","value":"spectral_filter","position":{"start":{"line":17,"column":1},"end":{"line":17,"column":1}},"key":"IqFJuCJjgF"},{"type":"text","value":" below implements this procedure using NumPy. After removing the time mean, it computes the real FFT (","position":{"start":{"line":17,"column":1},"end":{"line":17,"column":1}},"key":"vzkyIPjbNZ"},{"type":"inlineCode","value":"np.fft.rfft","position":{"start":{"line":17,"column":1},"end":{"line":17,"column":1}},"key":"sBDlJ81Hzu"},{"type":"text","value":") and converts each frequency bin to its corresponding period, (T = 1/f). A boolean mask is then applied to determine which Fourier coefficients are retained.","position":{"start":{"line":17,"column":1},"end":{"line":17,"column":1}},"key":"LojiXi1QML"}],"key":"zMrEDNd3GG"},{"type":"paragraph","position":{"start":{"line":19,"column":1},"end":{"line":19,"column":1}},"children":[{"type":"text","value":"The filtering options are:","position":{"start":{"line":19,"column":1},"end":{"line":19,"column":1}},"key":"odbJsokmcU"}],"key":"itwEUYkL8J"},{"type":"list","ordered":false,"spread":false,"position":{"start":{"line":21,"column":1},"end":{"line":24,"column":1}},"children":[{"type":"listItem","spread":true,"position":{"start":{"line":21,"column":1},"end":{"line":21,"column":1}},"children":[{"type":"paragraph","children":[{"type":"strong","position":{"start":{"line":21,"column":1},"end":{"line":21,"column":1}},"children":[{"type":"text","value":"Low-pass:","position":{"start":{"line":21,"column":1},"end":{"line":21,"column":1}},"key":"SYkEeJVEV4"}],"key":"GAPYG0GxTT"},{"type":"text","value":" specify ","position":{"start":{"line":21,"column":1},"end":{"line":21,"column":1}},"key":"StzODcy373"},{"type":"inlineCode","value":"period_min","position":{"start":{"line":21,"column":1},"end":{"line":21,"column":1}},"key":"EfMH9k8eIn"},{"type":"text","value":" only, retaining periods ","position":{"start":{"line":21,"column":1},"end":{"line":21,"column":1}},"key":"j7q0MTfY1f"},{"type":"inlineMath","value":"( T \\geq T_{\\min} )","position":{"start":{"line":21,"column":1},"end":{"line":21,"column":1}},"html":"<span class=\"katex\"><span class=\"katex-mathml\"><math xmlns=\"http://www.w3.org/1998/Math/MathML\"><semantics><mrow><mo stretchy=\"false\">(</mo><mi>T</mi><mo>≥</mo><msub><mi>T</mi><mi>min</mi><mo>⁡</mo></msub><mo stretchy=\"false\">)</mo></mrow><annotation encoding=\"application/x-tex\">( T \\geq T_{\\min} )</annotation></semantics></math></span><span class=\"katex-html\" aria-hidden=\"true\"><span class=\"base\"><span class=\"strut\" style=\"height:1em;vertical-align:-0.25em;\"></span><span class=\"mopen\">(</span><span class=\"mord mathnormal\" style=\"margin-right:0.13889em;\">T</span><span class=\"mspace\" style=\"margin-right:0.2778em;\"></span><span class=\"mrel\">≥</span><span class=\"mspace\" style=\"margin-right:0.2778em;\"></span></span><span class=\"base\"><span class=\"strut\" style=\"height:1em;vertical-align:-0.25em;\"></span><span class=\"mord\"><span class=\"mord mathnormal\" style=\"margin-right:0.13889em;\">T</span><span class=\"msupsub\"><span class=\"vlist-t vlist-t2\"><span class=\"vlist-r\"><span class=\"vlist\" style=\"height:0.3175em;\"><span style=\"top:-2.55em;margin-left:-0.1389em;margin-right:0.05em;\"><span class=\"pstrut\" style=\"height:2.7em;\"></span><span class=\"sizing reset-size6 size3 mtight\"><span class=\"mord mtight\"><span class=\"mop mtight\"><span class=\"mtight\">m</span><span class=\"mtight\">i</span><span class=\"mtight\">n</span></span></span></span></span></span><span class=\"vlist-s\">​</span></span><span class=\"vlist-r\"><span class=\"vlist\" style=\"height:0.15em;\"><span></span></span></span></span></span></span><span class=\"mclose\">)</span></span></span></span>","key":"XiOvgNEDBs"},{"type":"text","value":".","position":{"start":{"line":21,"column":1},"end":{"line":21,"column":1}},"key":"AWILd5olZj"}],"key":"RmCNK27LoQ"}],"key":"bOO5r50RoZ"},{"type":"listItem","spread":true,"position":{"start":{"line":22,"column":1},"end":{"line":22,"column":1}},"children":[{"type":"paragraph","children":[{"type":"strong","position":{"start":{"line":22,"column":1},"end":{"line":22,"column":1}},"children":[{"type":"text","value":"High-pass:","position":{"start":{"line":22,"column":1},"end":{"line":22,"column":1}},"key":"x0Xrt9v4lI"}],"key":"wzfPMujuj2"},{"type":"text","value":" specify ","position":{"start":{"line":22,"column":1},"end":{"line":22,"column":1}},"key":"Ta5Zawgvs0"},{"type":"inlineCode","value":"period_max","position":{"start":{"line":22,"column":1},"end":{"line":22,"column":1}},"key":"Iw74FC1ioH"},{"type":"text","value":" only, retaining periods ","position":{"start":{"line":22,"column":1},"end":{"line":22,"column":1}},"key":"NTKKWeqzvw"},{"type":"inlineMath","value":"(T \\leq T_{\\max})","position":{"start":{"line":22,"column":1},"end":{"line":22,"column":1}},"html":"<span class=\"katex\"><span class=\"katex-mathml\"><math xmlns=\"http://www.w3.org/1998/Math/MathML\"><semantics><mrow><mo stretchy=\"false\">(</mo><mi>T</mi><mo>≤</mo><msub><mi>T</mi><mi>max</mi><mo>⁡</mo></msub><mo stretchy=\"false\">)</mo></mrow><annotation encoding=\"application/x-tex\">(T \\leq T_{\\max})</annotation></semantics></math></span><span class=\"katex-html\" aria-hidden=\"true\"><span class=\"base\"><span class=\"strut\" style=\"height:1em;vertical-align:-0.25em;\"></span><span class=\"mopen\">(</span><span class=\"mord mathnormal\" style=\"margin-right:0.13889em;\">T</span><span class=\"mspace\" style=\"margin-right:0.2778em;\"></span><span class=\"mrel\">≤</span><span class=\"mspace\" style=\"margin-right:0.2778em;\"></span></span><span class=\"base\"><span class=\"strut\" style=\"height:1em;vertical-align:-0.25em;\"></span><span class=\"mord\"><span class=\"mord mathnormal\" style=\"margin-right:0.13889em;\">T</span><span class=\"msupsub\"><span class=\"vlist-t vlist-t2\"><span class=\"vlist-r\"><span class=\"vlist\" style=\"height:0.1514em;\"><span style=\"top:-2.55em;margin-left:-0.1389em;margin-right:0.05em;\"><span class=\"pstrut\" style=\"height:2.7em;\"></span><span class=\"sizing reset-size6 size3 mtight\"><span class=\"mord mtight\"><span class=\"mop mtight\"><span class=\"mtight\">m</span><span class=\"mtight\">a</span><span class=\"mtight\">x</span></span></span></span></span></span><span class=\"vlist-s\">​</span></span><span class=\"vlist-r\"><span class=\"vlist\" style=\"height:0.15em;\"><span></span></span></span></span></span></span><span class=\"mclose\">)</span></span></span></span>","key":"j8kZP4MWF0"},{"type":"text","value":".","position":{"start":{"line":22,"column":1},"end":{"line":22,"column":1}},"key":"q1igEtIdlT"}],"key":"vyvn5zuM4y"}],"key":"rcmhunlL0T"},{"type":"listItem","spread":true,"position":{"start":{"line":23,"column":1},"end":{"line":24,"column":1}},"children":[{"type":"paragraph","children":[{"type":"strong","position":{"start":{"line":23,"column":1},"end":{"line":23,"column":1}},"children":[{"type":"text","value":"Band-pass:","position":{"start":{"line":23,"column":1},"end":{"line":23,"column":1}},"key":"D81IPRN39J"}],"key":"mHrAUS3E3l"},{"type":"text","value":" specify both ","position":{"start":{"line":23,"column":1},"end":{"line":23,"column":1}},"key":"H5YXj9a3ii"},{"type":"inlineCode","value":"period_min","position":{"start":{"line":23,"column":1},"end":{"line":23,"column":1}},"key":"xYHV0MTnFf"},{"type":"text","value":" and ","position":{"start":{"line":23,"column":1},"end":{"line":23,"column":1}},"key":"xrIfhc8trB"},{"type":"inlineCode","value":"period_max","position":{"start":{"line":23,"column":1},"end":{"line":23,"column":1}},"key":"nltG453tPd"},{"type":"text","value":", retaining periods ","position":{"start":{"line":23,"column":1},"end":{"line":23,"column":1}},"key":"HvgXmVJLaI"},{"type":"inlineMath","value":"(T_{\\min} \\leq T \\leq T_{\\max})","position":{"start":{"line":23,"column":1},"end":{"line":23,"column":1}},"html":"<span class=\"katex\"><span class=\"katex-mathml\"><math xmlns=\"http://www.w3.org/1998/Math/MathML\"><semantics><mrow><mo stretchy=\"false\">(</mo><msub><mi>T</mi><mi>min</mi><mo>⁡</mo></msub><mo>≤</mo><mi>T</mi><mo>≤</mo><msub><mi>T</mi><mi>max</mi><mo>⁡</mo></msub><mo stretchy=\"false\">)</mo></mrow><annotation encoding=\"application/x-tex\">(T_{\\min} \\leq T \\leq T_{\\max})</annotation></semantics></math></span><span class=\"katex-html\" aria-hidden=\"true\"><span class=\"base\"><span class=\"strut\" style=\"height:1em;vertical-align:-0.25em;\"></span><span class=\"mopen\">(</span><span class=\"mord\"><span class=\"mord mathnormal\" style=\"margin-right:0.13889em;\">T</span><span class=\"msupsub\"><span class=\"vlist-t vlist-t2\"><span class=\"vlist-r\"><span class=\"vlist\" style=\"height:0.3175em;\"><span style=\"top:-2.55em;margin-left:-0.1389em;margin-right:0.05em;\"><span class=\"pstrut\" style=\"height:2.7em;\"></span><span class=\"sizing reset-size6 size3 mtight\"><span class=\"mord mtight\"><span class=\"mop mtight\"><span class=\"mtight\">m</span><span class=\"mtight\">i</span><span class=\"mtight\">n</span></span></span></span></span></span><span class=\"vlist-s\">​</span></span><span class=\"vlist-r\"><span class=\"vlist\" style=\"height:0.15em;\"><span></span></span></span></span></span></span><span class=\"mspace\" style=\"margin-right:0.2778em;\"></span><span class=\"mrel\">≤</span><span class=\"mspace\" style=\"margin-right:0.2778em;\"></span></span><span class=\"base\"><span class=\"strut\" style=\"height:0.8193em;vertical-align:-0.136em;\"></span><span class=\"mord mathnormal\" style=\"margin-right:0.13889em;\">T</span><span class=\"mspace\" style=\"margin-right:0.2778em;\"></span><span class=\"mrel\">≤</span><span class=\"mspace\" style=\"margin-right:0.2778em;\"></span></span><span class=\"base\"><span class=\"strut\" style=\"height:1em;vertical-align:-0.25em;\"></span><span class=\"mord\"><span class=\"mord mathnormal\" style=\"margin-right:0.13889em;\">T</span><span class=\"msupsub\"><span class=\"vlist-t vlist-t2\"><span class=\"vlist-r\"><span class=\"vlist\" style=\"height:0.1514em;\"><span style=\"top:-2.55em;margin-left:-0.1389em;margin-right:0.05em;\"><span class=\"pstrut\" style=\"height:2.7em;\"></span><span class=\"sizing reset-size6 size3 mtight\"><span class=\"mord mtight\"><span class=\"mop mtight\"><span class=\"mtight\">m</span><span class=\"mtight\">a</span><span class=\"mtight\">x</span></span></span></span></span></span><span class=\"vlist-s\">​</span></span><span class=\"vlist-r\"><span class=\"vlist\" style=\"height:0.15em;\"><span></span></span></span></span></span></span><span class=\"mclose\">)</span></span></span></span>","key":"t0e7Ay1EWB"},{"type":"text","value":".","position":{"start":{"line":23,"column":1},"end":{"line":23,"column":1}},"key":"aNu3vkBRuY"}],"key":"B7kbRBf9jn"}],"key":"AujC3NEuq3"}],"key":"GOfp4q3pJ8"},{"type":"paragraph","position":{"start":{"line":25,"column":1},"end":{"line":25,"column":1}},"children":[{"type":"text","value":"The zero-frequency (DC) component is always removed because the mean has already been subtracted. The filtered time series is then reconstructed with ","position":{"start":{"line":25,"column":1},"end":{"line":25,"column":1}},"key":"vVZX9hJcDX"},{"type":"inlineCode","value":"np.fft.irfft","position":{"start":{"line":25,"column":1},"end":{"line":25,"column":1}},"key":"PdRw2LHqob"},{"type":"text","value":".","position":{"start":{"line":25,"column":1},"end":{"line":25,"column":1}},"key":"VOTvjcWoCs"}],"key":"pLrUP84ET3"},{"type":"paragraph","position":{"start":{"line":27,"column":1},"end":{"line":27,"column":1}},"children":[{"type":"text","value":"Below, we apply these filters to the harmonic anomalies, using a 100-day cutoff to separate low- and high-frequency variability and a 20–90 day band-pass filter to isolate intraseasonal fluctuations, including signals associated with the Madden–Julian Oscillation (MJO).","position":{"start":{"line":27,"column":1},"end":{"line":27,"column":1}},"key":"AgqnLXPdHf"}],"key":"DKyD4w6PWT"}],"key":"BbVjCWKjxj"},{"type":"block","kind":"notebook-code","children":[{"type":"code","lang":"python","executable":true,"value":"def spectral_filter(series, period_min=None, period_max=None, dt=1.0):\n    \"\"\"Band-pass in period space; omit period_min or period_max for high/low pass.\"\"\"\n    mean = np.mean(series)\n    x = series - mean\n    n = len(x)\n    freqs = np.fft.rfftfreq(n, d=dt)\n    coeffs = np.fft.rfft(x)\n\n    with np.errstate(divide=\"ignore\"):\n        freq_periods = np.where(freqs > 0, 1.0 / freqs, np.inf)\n\n    keep = np.ones_like(freqs, dtype=bool)\n    if period_max is not None:\n        keep &= freq_periods <= period_max\n    if period_min is not None:\n        keep &= freq_periods >= period_min\n    keep[0] = False  # remove the DC (mean) component\n\n    coeffs_filtered = np.where(keep, coeffs, 0.0)\n    return np.fft.irfft(coeffs_filtered, n=n)\n\n\ncutoff = 100  # days\nbp_low, bp_high = 20, 90  # days\n\nlowpass = spectral_filter(anomalies, period_min=cutoff)\nhighpass = spectral_filter(anomalies, period_max=cutoff)\nbandpass = spectral_filter(anomalies, period_min=bp_low,\n                           period_max=bp_high)","key":"ImFfJDXxOp"},{"type":"outputs","id":"4aF8eiUX04aRJl4KYPbiu","children":[],"key":"ZBZ6nf2BVV"}],"key":"PToaCewQvy"},{"type":"block","kind":"notebook-content","children":[{"type":"paragraph","position":{"start":{"line":1,"column":1},"end":{"line":1,"column":1}},"children":[{"type":"text","value":"Compare the original series with each filtered version over two years. The low-pass trace follows the seasonal envelope; the high-pass trace removes it; the band-pass trace isolates intraseasonal swings.","position":{"start":{"line":1,"column":1},"end":{"line":1,"column":1}},"key":"V2qJq3QyFW"}],"key":"UTk4Qbl4mK"}],"key":"uaNQA9790T"},{"type":"block","kind":"notebook-code","children":[{"type":"code","lang":"python","executable":true,"value":"two_years = slice(0, int(365.25 * 2))\ntime_slice = olr_series.time[two_years]\n\nfig, axes = plt.subplots(4, 1, figsize=(10, 9), sharex=True)\npanels = [\n    (series[two_years], \"Original\", \"C0\"),\n    (lowpass[two_years], f\"Low-pass (periods > {cutoff} days)\", \"C1\"),\n    (highpass[two_years], f\"High-pass (periods < {cutoff} days)\", \"C2\"),\n    (bandpass[two_years], f\"Band-pass ({bp_low}–{bp_high} days)\", \"C3\"),\n]\nfor ax, (data, title, color) in zip(axes, panels):\n    ax.plot(time_slice, data, color=color, linewidth=0.8)\n    ax.set_ylabel(\"OLR (W/m$^2$)\")\n    ax.set_title(title)\naxes[-1].set_xlabel(\"Time\")\nfig.tight_layout()\nplt.show()","key":"xvxFyxHVQd"},{"type":"outputs","id":"QgQEh_yI_P4KCPy6RLDmA","children":[{"type":"output","children":[],"jupyter_data":{"output_type":"display_data","metadata":{},"data":{"text/plain":{"content":"<Figure size 1000x900 with 4 Axes>","content_type":"text/plain"},"image/png":{"content_type":"image/png","hash":"425fedae5892246f531acd023eea8f54","path":"/spectral-analysis-cookbook/_preview/42/build/425fedae5892246f531acd023eea8f54.png"}}},"key":"fONnRkQPUH"}],"key":"SCWWmhHeiY"}],"key":"krdAqv8jK6"},{"type":"block","kind":"notebook-code","children":[{"type":"code","lang":"python","executable":true,"value":"fig, ax = plt.subplots(figsize=(8, 4))\nfor filtered, label in [\n    (lowpass, f\"Low-pass (> {cutoff} d)\"),\n    (highpass, f\"High-pass (< {cutoff} d)\"),\n    (bandpass, f\"Band-pass ({bp_low}–{bp_high} d)\"),\n]:\n    p, pv, _ = power_spectrum(filtered)\n    ax.plot(p, pv, label=label, linewidth=1.6)\n\nax.set_xscale(\"log\")\nax.set_xlim(10, n_time)\nax.set_xlabel(\"Period (days)\")\nax.set_ylabel(\"Explained variance (%)\")\nax.set_title(\"Power spectra after filtering\")\nax.legend()\nplt.show()","key":"WtnYFd8FTq"},{"type":"outputs","id":"oSG7oXdxeDz0xco2fH2iE","children":[{"type":"output","children":[],"jupyter_data":{"output_type":"display_data","metadata":{},"data":{"text/plain":{"content":"<Figure size 800x400 with 1 Axes>","content_type":"text/plain"},"image/png":{"content_type":"image/png","hash":"35c7129b96ff95ba708352a47c0b17ca","path":"/spectral-analysis-cookbook/_preview/42/build/35c7129b96ff95ba708352a47c0b17ca.png"}}},"key":"gZGNbTF4To"}],"key":"bpDuc6zQtd"}],"key":"qIbZjrWwkj"},{"type":"block","kind":"notebook-content","children":[{"type":"thematicBreak","position":{"start":{"line":1,"column":1},"end":{"line":1,"column":1}},"key":"AiFJFeYld7"}],"key":"XWyPXfjTOj"},{"type":"block","kind":"notebook-content","children":[{"type":"heading","depth":2,"position":{"start":{"line":1,"column":1},"end":{"line":1,"column":1}},"children":[{"type":"text","value":"Summary","position":{"start":{"line":1,"column":1},"end":{"line":1,"column":1}},"key":"EB6cmBlCwJ"}],"identifier":"summary","label":"Summary","html_id":"summary","implicit":true,"key":"zbUVrDB7U1"},{"type":"paragraph","position":{"start":{"line":3,"column":1},"end":{"line":3,"column":1}},"children":[{"type":"text","value":"The ","position":{"start":{"line":3,"column":1},"end":{"line":3,"column":1}},"key":"hwM5APJtxR"},{"type":"strong","position":{"start":{"line":3,"column":1},"end":{"line":3,"column":1}},"children":[{"type":"text","value":"power spectrum","position":{"start":{"line":3,"column":1},"end":{"line":3,"column":1}},"key":"kEGZIKHf3A"}],"key":"YIezxmTu4B"},{"type":"text","value":" of a single-pixel time series reveals which time scales carry the most variance, often the annual cycle at ~365 days. ","position":{"start":{"line":3,"column":1},"end":{"line":3,"column":1}},"key":"FQya2uNYSN"},{"type":"strong","position":{"start":{"line":3,"column":1},"end":{"line":3,"column":1}},"children":[{"type":"text","value":"Spectral filters","position":{"start":{"line":3,"column":1},"end":{"line":3,"column":1}},"key":"ou0fbpnvP8"}],"key":"lgUkYo79sy"},{"type":"text","value":" multiply the Fourier coefficients by a mask: low-pass keeps slow variations, high-pass keeps fast ones, and band-pass targets a range such as 20–90 days for intraseasonal studies.","position":{"start":{"line":3,"column":1},"end":{"line":3,"column":1}},"key":"AQ1nOef2CO"}],"key":"oxw28pSELP"},{"type":"heading","depth":3,"position":{"start":{"line":5,"column":1},"end":{"line":5,"column":1}},"children":[{"type":"text","value":"What’s next?","position":{"start":{"line":5,"column":1},"end":{"line":5,"column":1}},"key":"y8qCbUbU1T"}],"identifier":"whats-next","label":"What’s next?","html_id":"whats-next","implicit":true,"key":"VtPr3kfVwK"},{"type":"paragraph","position":{"start":{"line":7,"column":1},"end":{"line":7,"column":1}},"children":[{"type":"text","value":"TBD","position":{"start":{"line":7,"column":1},"end":{"line":7,"column":1}},"key":"VmlSzoWhke"}],"key":"WCpL0bcpkc"}],"key":"dk4O8DgqFb"}],"key":"uaC5Zi1ccy"},"references":{"cite":{"order":["lee2014noaa"],"data":{"lee2014noaa":{"label":"lee2014noaa","enumerator":"1","html":"Lee, H.-T., & others. (2014). NOAA climate data record (CDR) of daily outgoing longwave radiation (OLR), version 1.2. <i>(No Title)</i>."}}}},"footer":{"navigation":{"prev":{"title":"The Discrete Fourier Transform","url":"/notebooks/discrete-fourier-transform","group":"Data Analysis Methods"},"next":{"title":"Limitation of the Fourier transform and Fourier series: The Gibbs Phenomenon","url":"/notebooks/gibbs-phenomenon","group":"Data Analysis Methods"}}},"domain":"http://localhost:3000"}